libbacktrace/__init__.py
libbacktrace/_libbacktrace.cpython-310-x86_64-linux-gnu.so
libbacktrace_python-0.2.1.dist-info/METADATA
libbacktrace_python-0.2.1.dist-info/WHEEL
libbacktrace_python-0.2.1.dist-info/RECORD
