Metadata-Version: 2.1
Name: libbacktrace-python
Version: 0.2.1
Summary: Python bindings for libbacktrace - native stack traces with DWARF symbols
Keywords: backtrace,stacktrace,debug,crash,dwarf,symbols
Author: Retrace Software
License: Apache-2.0
Classifier: Development Status :: 4 - Beta
Classifier: Intended Audience :: Developers
Classifier: License :: OSI Approved :: Apache Software License
Classifier: Operating System :: POSIX :: Linux
Classifier: Operating System :: MacOS :: MacOS X
Classifier: Programming Language :: Python :: 3
Classifier: Programming Language :: Python :: 3.9
Classifier: Programming Language :: Python :: 3.10
Classifier: Programming Language :: Python :: 3.11
Classifier: Programming Language :: Python :: 3.12
Classifier: Programming Language :: C
Classifier: Topic :: Software Development :: Debuggers
Classifier: Topic :: System :: Logging
Project-URL: Homepage, https://github.com/retracesoftware/libbacktrace-python
Project-URL: Repository, https://github.com/retracesoftware/libbacktrace-python
Project-URL: Issues, https://github.com/retracesoftware/libbacktrace-python/issues
Requires-Python: >=3.9
